Metadata-Version: 2.1
Name: get-gifNimage
Version: 0.3.7
Summary: Downloading image from URL, displaying from the drive
Home-page: https://github.com/Drill-N-Bass/get_gifNimage.git
Author: Pawel Pedryc
Author-email: pawel.pedryc@gmail.com
License: UNKNOWN
Keywords: get_gifNimage
Platform: UNKNOWN
Classifier: Development Status :: 5 - Production/Stable
Classifier: Intended Audience :: Education
Classifier: Operating System :: Microsoft :: Windows :: Windows 10
Classifier: Programming Language :: Python :: 3
